src/__init__.py
src/cvtools/__init__.py
src/cvtools/color_filter.py
src/cvtools/color_picker.py
src/cvtools/color_slicing.py
src/cvtools/_imwrite/__init__.py
src/cvtools/_imwrite/imwrite_tif.py
src/cvtools/filetools/__init__.py
src/cvtools/imread/__init__.py
src/cvtools/imread/imread_nd2.py
src/cvtools/imread/imread_tif.py
src/cvtools/imread/metadata.py
src/cvtools/roi/__init__.py
src/cvtools/roi/select.py
src/graphs/__init__.py
src/graphs/markov.py
src/ntheory/__init__.py
testpyjacket-0.1.1.dist-info/LICENSE
testpyjacket-0.1.1.dist-info/METADATA
testpyjacket-0.1.1.dist-info/WHEEL
testpyjacket-0.1.1.dist-info/top_level.txt
testpyjacket-0.1.1.dist-info/RECORD
